{"chunk_definitions":[{"row":9,"row_count":1,"visible":true,"expansion_state":0,"options":{"engine":"r","label":"setup","include":false},"document_id":"5DF7F314","chunk_id":"csetup_chunk","chunk_label":"setup"},{"row":18,"row_count":1,"visible":true,"expansion_state":0,"options":{"engine":"r","label":"unnamed-chunk-10"},"document_id":"5DF7F314","chunk_id":"cmutkwil9b028","chunk_label":"unnamed-chunk-1"},{"row":79,"row_count":1,"visible":true,"expansion_state":0,"options":{"engine":"r","label":"unnamed-chunk-21"},"document_id":"5DF7F314","chunk_id":"c2pl3a0y0awqh","chunk_label":"unnamed-chunk-6"},{"row":99,"row_count":1,"visible":true,"expansion_state":0,"options":{"engine":"r","label":"unnamed-chunk-22"},"document_id":"5DF7F314","chunk_id":"cbk20bdju99f1","chunk_label":"unnamed-chunk-7"},{"row":113,"row_count":1,"visible":true,"expansion_state":0,"options":{"engine":"r","label":"unnamed-chunk-23"},"document_id":"5DF7F314","chunk_id":"cwg1gyak9u1t3","chunk_label":"unnamed-chunk-8"},{"row":128,"row_count":1,"visible":true,"expansion_state":0,"options":{"engine":"r","label":"unnamed-chunk-24"},"document_id":"5DF7F314","chunk_id":"cc1zaatyrjwmz","chunk_label":"unnamed-chunk-9"},{"row":145,"row_count":1,"visible":true,"expansion_state":0,"options":{"engine":"r","label":"unnamed-chunk-25"},"document_id":"5DF7F314","chunk_id":"cqt6venvurd3a","chunk_label":"unnamed-chunk-10"},{"row":151,"row_count":1,"visible":true,"expansion_state":0,"options":{"engine":"r","label":"unnamed-chunk-26"},"document_id":"5DF7F314","chunk_id":"czsj8ns00fliv","chunk_label":"unnamed-chunk-11"},{"row":165,"row_count":1,"visible":true,"expansion_state":0,"options":{"engine":"r","label":"unnamed-chunk-27"},"document_id":"5DF7F314","chunk_id":"cun90tgzxft61","chunk_label":"unnamed-chunk-12"},{"row":173,"row_count":1,"visible":true,"expansion_state":0,"options":{"engine":"r","label":"unnamed-chunk-603"},"document_id":"5DF7F314","chunk_id":"c8hwxfvjifj6w","chunk_label":"unnamed-chunk-13"},{"row":212,"row_count":1,"visible":true,"expansion_state":0,"options":{"engine":"r","label":"unnamed-chunk-604"},"document_id":"5DF7F314","chunk_id":"chlp0bllsrvge","chunk_label":"unnamed-chunk-14"},{"row":271,"row_count":1,"visible":true,"expansion_state":0,"options":{"engine":"r","warning":false,"label":"unnamed-chunk-38"},"document_id":"5DF7F314","chunk_id":"c1bmxg7y92fam","chunk_label":"unnamed-chunk-16"},{"row":321,"row_count":1,"visible":true,"expansion_state":0,"options":{"engine":"r","label":"unnamed-chunk-758"},"document_id":"5DF7F314","chunk_id":"ccia6k2n78l1h","chunk_label":"unnamed-chunk-18"},{"row":350,"row_count":1,"visible":true,"expansion_state":0,"options":{"engine":"r","warning":false,"label":"unnamed-chunk-761"},"document_id":"5DF7F314","chunk_id":"cy465n559y4ig","chunk_label":"unnamed-chunk-19"},{"row":382,"row_count":1,"visible":true,"expansion_state":0,"options":{"engine":"r","label":"unnamed-chunk-616"},"document_id":"5DF7F314","chunk_id":"cwhhjqj5djgus","chunk_label":"unnamed-chunk-20"},{"row":389,"row_count":1,"visible":true,"expansion_state":0,"options":{"engine":"r","label":"unnamed-chunk-617"},"document_id":"5DF7F314","chunk_id":"c1o13uidel6fi","chunk_label":"unnamed-chunk-21"},{"row":404,"row_count":1,"visible":true,"expansion_state":0,"options":{"engine":"r","warning":false,"label":"unnamed-chunk-639"},"document_id":"5DF7F314","chunk_id":"ccu1ofdn6sqmv","chunk_label":"unnamed-chunk-22"},{"row":442,"row_count":1,"visible":true,"expansion_state":0,"options":{"engine":"r","warning":false,"label":"unnamed-chunk-640"},"document_id":"5DF7F314","chunk_id":"cq087qyd0szeg","chunk_label":"unnamed-chunk-23"},{"row":468,"row_count":1,"visible":true,"expansion_state":0,"options":{"engine":"r","warning":false,"label":"unnamed-chunk-641"},"document_id":"5DF7F314","chunk_id":"cx5ztyauf3nub","chunk_label":"unnamed-chunk-24"},{"row":593,"row_count":1,"visible":true,"expansion_state":0,"options":{"engine":"r","label":"unnamed-chunk-735"},"document_id":"5DF7F314","chunk_id":"cs2zdpwz039ry","chunk_label":"unnamed-chunk-26"},{"row":606,"row_count":1,"visible":true,"expansion_state":0,"options":{"engine":"r","label":"unnamed-chunk-757"},"document_id":"5DF7F314","chunk_id":"c1b17qe3b825v","chunk_label":"unnamed-chunk-27"}],"doc_write_time":1715209442,"working_dir":null,"default_chunk_options":{"echo":true},"chunk_rendered_width":626}